pn5180/__init__.py
pn5180/__main__.py
pn5180/definitions.py
pn5180/sensor.py
pn5180pi-0.1.2.dist-info/WHEEL
pn5180pi-0.1.2.dist-info/METADATA
pn5180pi-0.1.2.dist-info/license_files/LICENSE
pn5180pi-0.1.2.dist-info/RECORD
