Metadata-Version: 2.1
Name: pn5180pi
Version: 0.1.2
Summary: PN5180 NFC Sensor Driver Written for Raspberry Pi
License: MIT
Author-email: Connor Luebbehusen <connorluebbehusen@gmail.com>
Requires-Python: >=3.9
Requires-Dist: pigpio>=1.78
